{"economicalBowlers":{"2008":{"P Kumar":8.42,"Z Khan":8.79,"AA Noffke":10.25,"JH Kallis":9.38,"SB Joshi":8.95,"CL White":24,"AB Dinda":6.82,"I Sharma":8.25,"AB Agarkar":8.12,"SC Ganguly":6.6,"LR Shukla":10.5,"B Lee":7.38,"S Sreesanth":8.81,"JR Hopes":10.18,"IK Pathan":6.81,"K Goel":12.5,"PP Chawla":8.46,"WA Mota":12,"JDP Oram":9.31,"MS Gony":7.6,"M Muralitharan":7.17,"P Amarnath":10.95,"Joginder Sharma":9.77,"GD McGrath":6.78,"B Geeves":11.38,"MF Maharoof":7.08,"R Bhatia":8.41,"DL Vettori":6.75,"MM Patel":7.69,"SR Watson":7.29,"SK Trivedi":8.48,"SK Warne":7.87,"YK Pathan":8.27,"D Salunkhe":10.21,"R Vinay Kumar":7.96,"B Akhil":7.96,"A Nehra":7.96,"SM Pollock":6.67,"DS Kulkarni":8.2,"ST Jayasuriya":7.76,"Harbhajan Singh":8.4,"AM Nayar":9.86,"M Kartik":9,"Mohammad Hafeez":7.1,"DJ Hussey":10.31,"WPUJC Vaas":8.59,"RP Singh":8.94,"SB Styris":7.44,"SB Bangar":8.84,"A Symonds":15.51,"PP Ojha":8.08,"Pankaj Singh":10.75,"Mohammad Asif":9.59,"VY Mahesh":9.01,"Shahid Afridi":7.9,"DJ Bravo":8.39,"VS Yeligati":12.2,"MA Khote":10.4,"D Kalyankrishna":11,"VRV Singh":8.85,"Sohail Tanvir":6.68,"A Kumble":8.19,"DNT Zoysa":9.09,"SD Chitnis":10.33,"Yuvraj Singh":9.44,"Shoaib Malik":10.24,"DW Steyn":6.97,"JA Morkel":8.63,"CRD Fernando":8.2,"V Kohli":8.09,"V Sehwag":12.18,"Gagandeep Singh":10.14,"Y Venugopal Rao":9.79,"Umar Gul":8.8,"PJ Sangwan":9.21,"M Ntini":7.34,"DP Vijaykumar":8.09,"DB Ravi Teja":9.5,"LPC Silva":21,"DJ Thornely":5.71,"RR Raje":8.69,"SK Raina":9,"S Vidyut":11,"L Balaji":8.88,"CK Kapugedera":17.29,"DR Smith":7.55,"AD Mascarenhas":7.75,"A Mishra":7.06,"Shoaib Akhtar":7.71,"Iqbal Abdulla":7.33,"RR Powar":7.75,"PM Sarvesh Kumar":8.4,"Abdur Razzak":14.5,"RA Jadeja":9.69,"TM Dilshan":3,"RG Sharma":6.5,"A Nel":10.33,"BAW Mendis":6},"2009":{"MS Gony":10.18,"T Thushara":7.63,"A Flintoff":9.64,"JDP Oram":8.97,"Joginder Sharma":8.14,"SL Malinga":6.75,"Z Khan":6.86,"DJ Bravo":7.99,"RR Raje":10.54,"Harbhajan Singh":6.18,"ST Jayasuriya":8.68,"AD Mascarenhas":6.88,"Kamran Khan":7.93,"MM Patel":7.03,"T Henderson":6.83,"SK Warne":7.38,"YK Pathan":7.09,"P Kumar":8.07,"DW Steyn":6.89,"R Vinay Kumar":8.44,"JD Ryder":7.12,"A Kumble":5.97,"DP Nannes":7.76,"AM Salvi":8.12,"PJ Sangwan":8.01,"VY Mahesh":12.5,"DL Vettori":8.03,"IK Pathan":7.91,"YA Abdulla":8.71,"VS Malik":8.33,"VRV Singh":9.22,"PP Chawla":7.12,"FH Edwards":6.86,"RP Singh":7.21,"Harmeet Singh":8.67,"PP Ojha":6.71,"SB Styris":8,"AB Dinda":8.13,"I Sharma":7.05,"M Kartik":6.09,"SC Ganguly":8.17,"AB Agarkar":9.45,"CH Gayle":7.75,"MC Henriques":8.79,"JH Kallis":7.87,"V Kohli":7.67,"KP Pietersen":6.77,"LRPL Taylor":13,"L Balaji":8.57,"JA Morkel":8.25,"M Muralitharan":5.34,"LR Shukla":7.29,"RS Bopara":3.75,"A Nehra":6.94,"MK Tiwary":11,"Anureet Singh":9.4,"BAW Mendis":8.16,"RA Jadeja":6.69,"RR Bose":12,"Yuvraj Singh":7.1,"Pankaj Singh":9.29,"DS Kulkarni":8.04,"DR Smith":9.14,"RG Sharma":7.09,"Y Venugopal Rao":8.2,"A Mishra":7.11,"KP Appanna":7.58,"B Akhil":7.27,"RR Powar":6.57,"Shoaib Ahmed":9.06,"SK Raina":6.11,"BJ Hodge":8.35,"AM Nayar":7,"SR Tendulkar":9.83,"TM Dilshan":6.19,"RE van der Merwe":7.74,"JP Duminy":5.49,"K Goel":7.75,"WA Mota":6.89,"SK Trivedi":7.6,"S Tyagi":7.53,"GR Napier":7,"SM Harwood":7.4,"AS Raut":9.25,"R Bhatia":7.06,"SB Jakati":7.76,"D du Preez":8,"RJ Harris":7.58,"TL Suman":7.2,"S Sreesanth":8.52,"A Singh":5.71,"M Morkel":5.71,"LA Carseldine":6,"B Lee":5.65,"A Symonds":6.75,"A Mithun":10.5,"C Nanda":7.25,"SS Sarkar":8.16,"WPUJC Vaas":8.88,"AD Mathews":13.71,"DJ Hussey":8.5,"AM Rahane":5,"J Botha":6.33,"MF Maharoof":6.7,"Mashrafe Mortaza":14.75,"AB McDonald":7.33,"Y Nagar":10,"CK Langeveldt":3.75,"R Ashwin":3.5,"RA Shaikh":11,"Jaskaran Singh":10.67,"V Sehwag":25},"2010":{"WPUJC Vaas":6.68,"RP Singh":9.17,"Jaskaran Singh":10.14,"PP Ojha":7.46,"A Symonds":7.26,"TL Suman":12,"CK Langeveldt":8.36,"I Sharma":9.68,"LR Shukla":9,"M Kartik":6.69,"AD Mathews":8.45,"BJ Hodge":8.2,"AD Mascarenhas":8.25,"SW Tait":8.79,"Kamran Khan":8.83,"A Uniyal":11.17,"SK Warne":7.78,"AA Jhunjhunwala":11.19,"YK Pathan":7.47,"Z Khan":8.03,"R McLaren":8.26,"SL Malinga":7.35,"AG Murtaza":7.75,"R Sathish":10.13,"ST Jayasuriya":7.56,"DP Nannes":6.84,"MF Maharoof":8.75,"PJ Sangwan":8.39,"A Mishra":7,"VY Mahesh":7.67,"TM Dilshan":8.57,"IK Pathan":9.39,"S Sreesanth":10.05,"YA Abdulla":9.8,"PP Chawla":7.57,"Yuvraj Singh":6.74,"RR Powar":7.09,"SC Ganguly":10.75,"RS Gavaskar":8,"P Kumar":8.71,"JH Kallis":8.49,"DW Steyn":7.03,"A Kumble":6.66,"RE van der Merwe":6.75,"V Kohli":9.56,"JA Morkel":8.6,"S Tyagi":10.17,"M Muralitharan":7.32,"R Ashwin":6.42,"L Balaji":9.17,"JM Kemp":7.91,"RG Sharma":8.37,"S Ladda":9.6,"MM Patel":9.08,"R Vinay Kumar":8.75,"Bipul Sharma":9.4,"RS Bopara":10.15,"SE Bond":7.26,"MS Gony":11.5,"SK Raina":7.59,"DJ Bravo":8.83,"KA Pollard":7.46,"Harbhajan Singh":7.2,"M Morkel":9.43,"S Narwal":11.87,"Joginder Sharma":11.13,"UT Yadav":8,"R Bhatia":8.5,"SJ Srivastava":9.52,"AB Dinda":6.69,"SK Trivedi":7.49,"AC Voges":8.44,"Y Nagar":9.33,"MC Henriques":8.75,"R Sharma":8.23,"J Theron":8.21,"CH Gayle":9.56,"SB Jakati":7.89,"NLTC Perera":19,"B Lee":10.62,"VS Malik":9.21,"AB Agarkar":9.41,"Iqbal Abdulla":7.29,"DJ Hussey":8.1,"AB McDonald":9.86,"T Thushara":7.1,"KAJ Roach":10,"PD Collingwood":6.81,"K Goel":7,"C Ganapathy":13,"KP Pietersen":7.7,"V Sehwag":4.06,"Harmeet Singh":7.38,"Y Venugopal Rao":10,"MB Parmar":11,"SR Watson":8.41,"SB Wagh":16,"DE Bollinger":6.87,"RJ Harris":7.79,"JD Unadkat":8.23,"A Mithun":13,"KP Appanna":7.29,"CL White":19,"DL Vettori":8.4,"DR Smith":9.39,"AP Dole":10.36,"AN Ahmed":13,"FY Fazal":10,"BAW Mendis":8.5,"MR Marsh":8.9,"L Ablish":9.25,"JP Duminy":6.73,"S Sriram":12,"A Nehra":7.29,"DS Kulkarni":10,"CRD Fernando":7.47,"Pankaj Singh":10.38,"AJ Finch":4.29,"VRV Singh":13.67,"MK Tiwary":11,"STR Binny":9,"ND Doshi":4.25,"B Akhil":6},"2011":{"Iqbal Abdulla":6.26,"YK Pathan":6.26,"L Balaji":8.64,"JH Kallis":7.08,"S Ladda":10.5,"R Bhatia":6.66,"JA Morkel":8.67,"TG Southee":8.79,"R Ashwin":6.32,"S Randiv":7.69,"SB Jakati":7.65,"SK Raina":7.6,"JDP Oram":11.5,"A Singh":7.79,"J Botha":6.72,"SK Trivedi":8.61,"SK Warne":6.34,"AL Menaria":8.07,"STR Binny":11,"PP Ojha":7.63,"DW Steyn":6.68,"I Sharma":7.36,"DT Christian":7.82,"A Mishra":6.92,"Z Khan":7.88,"DP Nannes":7.75,"DL Vettori":6.1,"TM Dilshan":9,"A Mithun":9.56,"V Kohli":8.24,"AUK Pathan":8.91,"RP Singh":7.3,"S Sreesanth":6.66,"RA Jadeja":7.31,"R Vinay Kumar":7.72,"M Muralitharan":7.63,"RV Gomez":8.33,"Harbhajan Singh":7.04,"SL Malinga":6.24,"AG Murtaza":6.1,"MM Patel":6.94,"KA Pollard":8.64,"JEC Franklin":9.74,"AB Dinda":9.35,"M Morkel":7.81,"IK Pathan":7.7,"UT Yadav":9.56,"RE van der Merwe":6.34,"AJ Finch":6.5,"AC Thomas":7.79,"SB Wagh":8.19,"WD Parnell":7.57,"M Kartik":8.16,"JD Ryder":7.76,"M Manhas":6,"R Sharma":5.56,"P Kumar":7.67,"NJ Rimmington":6.67,"R McLaren":10.11,"PP Chawla":8.23,"AM Nayar":9.34,"DB Ravi Teja":9,"JP Duminy":8.28,"JD Unadkat":8.39,"RN ten Doeschate":7,"SW Tait":9.24,"S Nadeem":7.63,"RJ Harris":8.53,"BA Bhatt":8.37,"SB Styris":13,"Yuvraj Singh":6.66,"BJ Hodge":7,"JJ van der Wath":11.17,"S Aravind":8.2,"R Ninan":10.83,"MS Gony":9.56,"B Lee":7.7,"Shakib Al Hasan":6.94,"SR Watson":6.89,"ND Doshi":11.63,"NLTC Perera":8.14,"RR Powar":9.33,"R Sathish":7.94,"VS Malik":7,"PC Valthaty":7.9,"Y Venugopal Rao":13,"JR Hopes":8.66,"AA Jhunjhunwala":11,"DE Bollinger":7.3,"Y Nagar":13.4,"Harmeet Singh":7.57,"S Dhawan":6,"AN Ahmed":8.9,"AS Raut":8,"Joginder Sharma":11.33,"RG Sharma":13.25,"J Syed Mohammad":8.53,"CH Gayle":7.28,"MK Tiwary":11.5,"SJ Srivastava":9.35,"DJ Hussey":12.67,"VR Aaron":6.92,"AB Agarkar":8.74,"NL McCullum":7,"JE Taylor":8.56,"KMDN Kulasekara":8.67,"MR Marsh":7.2,"Kamran Khan":15.67,"B Akhil":11,"Bipul Sharma":6.67,"TL Suman":8.33,"A Symonds":10.25,"P Parameswaran":8.74,"DS Kulkarni":7.8,"AM Salvi":8.38,"I Malhotra":23,"B Chipli":20,"L Ablish":13,"B Kumar":6.18,"DJ Bravo":7.95,"CK Langeveldt":8.36,"AA Kazi":10.5,"Pankaj Singh":12,"LRPL Taylor":11,"AB McDonald":11.5,"Anand Rajan":10,"S Sriram":25,"P Prasanth":18,"Y Gnaneswara Rao":7,"AA Chavan":6.2,"S Rana":3,"JP Faulkner":5,"SS Mundhe":6,"RW Price":11},"2012":{"SL Malinga":6.4,"AN Ahmed":8.5,"Harbhajan Singh":7.2,"JEC Franklin":8.4,"PP Ojha":7.4,"KA Pollard":8.03,"JA Morkel":7.92,"DE Bollinger":8.89,"R Ashwin":6.67,"RA Jadeja":7.94,"DJ Bravo":8.18,"SB Jakati":8.22,"IK Pathan":7.95,"RE van der Merwe":6,"M Morkel":7.4,"UT Yadav":7.52,"GJ Maxwell":7.33,"S Nadeem":7.11,"B Lee":7.97,"M de Lange":10.8,"Iqbal Abdulla":6.68,"JH Kallis":7.59,"R Bhatia":7.52,"YK Pathan":8.36,"MM Patel":8.01,"M Kartik":7.42,"AB Dinda":7.13,"MN Samuels":7.57,"WD Parnell":6.33,"R Sharma":8.24,"B Kumar":7.51,"P Kumar":7.06,"JP Faulkner":9.25,"PP Chawla":7.46,"Bipul Sharma":10.7,"Harmeet Singh":8.78,"PC Valthaty":16,"SK Trivedi":7.44,"J Botha":7.41,"A Singh":9.65,"KK Cooper":7.79,"BJ Hodge":11,"AA Chavan":8.96,"DAJ Bracewell":8,"Z Khan":7.8,"R Vinay Kumar":8.74,"AB McDonald":6.3,"DL Vettori":6.89,"M Muralitharan":6.6,"HV Patel":8.59,"Ankit Sharma":6.91,"DW Steyn":6.21,"MS Gony":9.04,"DT Christian":8.89,"DJ Harris":8.67,"TP Sudhindra":11.74,"SK Raina":7.57,"F du Plessis":16,"SP Narine":5.61,"AD Mascarenhas":6.88,"A Nehra":8.56,"JD Ryder":10.57,"Anand Rajan":9.55,"A Mishra":8.11,"CL White":9,"V Kohli":16.33,"L Balaji":5.63,"RN ten Doeschate":8,"Shakib Al Hasan":6.77,"KP Pietersen":8.83,"GB Hogg":7.28,"RR Bhatkal":17.5,"P Awana":8.13,"AD Mathews":7.5,"AL Menaria":6.9,"AB Agarkar":9.35,"V Pratap Singh":8.82,"JP Duminy":8.67,"KMDN Kulasekara":6.86,"VY Mahesh":8.89,"JD Unadkat":10.67,"BA Bhatt":8.67,"S Aravind":16,"CH Gayle":14.36,"Pankaj Singh":8.14,"RP Singh":8,"CJ McKay":8.57,"TM Dilshan":11.14,"KP Appanna":8.76,"AD Russell":10.13,"VR Aaron":9,"S Dhawan":10,"A Ashish Reddy":8.76,"Azhar Mahmood":7.76,"STR Binny":7.8,"V Sehwag":11.25,"Y Nagar":10,"AC Thomas":8.29,"SC Ganguly":9.7,"DJ Hussey":7.44,"NLTC Perera":10.8,"A Chandila":6.21,"P Negi":6.95,"LJ Wright":12,"RJ Peterson":8.75,"J Theron":8.25,"R Shukla":10.67,"LR Shukla":6,"SR Watson":7.17,"RJ Harris":7.56,"AM Nayar":16,"AUK Pathan":14,"MJ Clarke":6.55,"AA Jhunjhunwala":6.5,"BW Hilfenhaus":7.12,"SW Tait":6.74,"DR Smith":7.54,"A Mithun":11.33,"P Parameswaran":8.9,"J Syed Mohammad":9.43,"PJ Sangwan":10.5,"SPD Smith":15,"RR Powar":10.67,"RG Sharma":16,"K Upadhyay":8.25,"Y Venugopal Rao":13,"AG Murtaza":5.5,"DS Kulkarni":8,"Sunny Gupta":15.67},"2013":{"B Lee":7.42,"JH Kallis":7.68,"L Balaji":7.98,"SP Narine":5.52,"R Bhatia":7.62,"LR Shukla":7.33,"IK Pathan":7.62,"A Nehra":8.86,"UT Yadav":9.06,"S Nadeem":6,"J Botha":6.84,"AD Russell":9.71,"MG Johnson":7.36,"MM Patel":9.2,"JJ Bumrah":10.57,"JDP Oram":7,"Harbhajan Singh":6.66,"KA Pollard":9.42,"JD Unadkat":7.61,"DT Christian":9.33,"R Vinay Kumar":8.53,"M Muralitharan":8.35,"M Kartik":7.44,"MN Samuels":8.5,"B Kumar":6.68,"AB Dinda":9.51,"AD Mathews":7.9,"R Sharma":6.88,"Yuvraj Singh":6.91,"DW Steyn":5.96,"I Sharma":7.89,"NLTC Perera":8.21,"A Mishra":6.37,"CL White":8,"A Ashish Reddy":10.65,"S Badree":8.75,"S Sreesanth":7.89,"SK Trivedi":7.1,"KK Cooper":8.44,"R Shukla":10,"STR Binny":6.79,"DP Nannes":8.32,"AS Rajpoot":9.25,"DJ Bravo":8.08,"B Laughlin":10.29,"RA Jadeja":7.55,"R Ashwin":6.84,"PP Ojha":7.47,"P Kumar":6.99,"RJ Harris":6.17,"Azhar Mahmood":7.64,"P Awana":7.7,"PP Chawla":7.42,"MR Marsh":9.52,"GH Vihari":6.5,"Ankit Sharma":8.5,"MC Henriques":8.83,"TM Dilshan":10,"Mohammed Shami":8.78,"SW Tait":10.3,"M Morkel":8.53,"BMAJ Mendis":7.2,"SL Malinga":7.41,"CH Morris":8.2,"R Sathish":13,"RP Singh":8.44,"R McLaren":13.57,"PJ Sangwan":13,"Harmeet Singh (2)":8.5,"JP Faulkner":6.9,"Anand Rajan":5.38,"S Kaul":7.88,"AJ Finch":12.25,"R Dhawan":7.67,"MM Sharma":6.45,"R Rampaul":7.29,"J Syed Mohammad":9.2,"KV Sharma":6.75,"SMSM Senanayake":6.59,"A Chandila":6.32,"AM Nayar":7.38,"MS Gony":9.32,"DJ Hussey":8.45,"AB McDonald":8.5,"AA Chavan":7,"V Sehwag":9,"AB Agarkar":9.3,"JA Morkel":6.96,"AD Mascarenhas":6.25,"YK Pathan":8.22,"SR Watson":7.66,"RE van der Merwe":6.45,"DR Smith":11.8,"BAW Mendis":6.5,"LJ Wright":10.27,"JO Holder":8.65,"IC Pandey":12.5,"AG Murtaza":9.6,"CH Gayle":10.25,"Sandeep Sharma":8.13,"YS Chahal":8.75,"Iqbal Abdulla":7.54,"DJG Sammy":7.57,"S Ladda":9,"BA Bhatt":6.4,"Harmeet Singh":7.85,"DS Kulkarni":8.2,"KW Richardson":8.7,"RG Sharma":4.5,"SK Raina":11.5,"TL Suman":8,"S Narwal":8.5,"GB Hogg":9.3,"Z Khan":7.83,"P Suyal":7.33,"K Upadhyay":9.6,"WD Parnell":9.51,"PV Tambe":8.27,"P Negi":7,"BJ Rohrer":12,"AN Ahmed":6.43,"Bipul Sharma":5.25,"Parvez Rasool":5.8,"RN ten Doeschate":8,"GJ Maxwell":12,"A Mithun":9.25,"VS Malik":5.9,"RV Gomez":5,"MG Neser":15.5,"BJ Hodge":3,"NM Coulter-Nile":7.25,"AC Gilchrist":0},"2014":{"Z Khan":6.99,"SL Malinga":6.82,"CJ Anderson":10.44,"PP Ojha":8.37,"Harbhajan Singh":6.64,"KA Pollard":10.6,"R Vinay Kumar":9.19,"M Morkel":7.83,"SP Narine":6.65,"Shakib Al Hasan":6.78,"JH Kallis":8.77,"PP Chawla":7.7,"MA Starc":7.81,"JA Morkel":7.94,"VR Aaron":8.43,"YS Chahal":7.07,"AB Dinda":8.74,"Yuvraj Singh":8.43,"JP Duminy":7.33,"Mohammed Shami":8.66,"WD Parnell":7.79,"S Nadeem":8.26,"R Sharma":10.83,"JDS Neesham":10.67,"AR Patel":6.42,"P Awana":10.55,"MG Johnson":8.41,"L Balaji":8.97,"R Dhawan":7.88,"GJ Maxwell":12.09,"A Nehra":9.53,"MM Sharma":8.49,"R Ashwin":7.45,"P Negi":10.86,"RA Jadeja":8.21,"DR Smith":9.9,"DS Kulkarni":8.37,"KW Richardson":7.74,"JP Faulkner":10.2,"PV Tambe":7.45,"R Bhatia":7.55,"STR Binny":7.22,"DW Steyn":7.88,"B Kumar":6.81,"I Sharma":9.18,"DJG Sammy":11.36,"A Mishra":9.12,"KV Sharma":7.76,"JJ Bumrah":7.74,"NM Coulter-Nile":6.75,"JD Unadkat":8.92,"M Kartik":11.38,"M Vijay":13,"IC Pandey":7.88,"BW Hilfenhaus":9.11,"IK Pathan":8.83,"Sandeep Sharma":8.91,"TG Southee":7.8,"SR Watson":8.05,"SK Raina":7.5,"M Muralitharan":7.81,"UT Yadav":8.47,"LR Shukla":9.43,"Y Venugopal Rao":8,"R Rampaul":6.17,"RG Sharma":8.67,"Iqbal Abdulla":9,"AD Russell":10.8,"HV Patel":10.73,"RN ten Doeschate":7,"R Tewatia":6.56,"P Suyal":11.67,"SA Yadav":8,"S Kaul":10.46,"MC Henriques":9.6,"Shivam Sharma":7.56,"Imran Tahir":8.45,"R Shukla":11.67,"S Badree":7.36,"P Kumar":6.75,"V Shankar":19,"Ankit Sharma":5.5,"KK Cooper":8.11,"AN Ahmed":8.37,"YK Pathan":10,"LMP Simmons":11.33,"MK Tiwary":14,"BCJ Cutting":7.75,"S Rana":8,"DJ Hussey":13.41,"K Santokie":11.38,"S Gopal":8.07,"BE Hendricks":10.58,"Parvez Rasool":9.22,"PJ Cummins":7.25,"JW Hastings":9.67,"M de Lange":8.25,"VS Malik":9.67,"Karanveer Singh":8.2,"SB Jakati":11.18,"JO Holder":11.67},"2015":{"UT Yadav":9.21,"M Morkel":7.57,"Shakib Al Hasan":8.79,"SP Narine":7.69,"AD Russell":8.16,"PP Chawla":7.86,"SL Malinga":7.55,"R Vinay Kumar":8.53,"CJ Anderson":8.25,"JJ Bumrah":12.27,"PP Ojha":11.5,"Harbhajan Singh":7.86,"JA Morkel":9.42,"NM Coulter-Nile":7.79,"DJ Muthuswami":7.71,"Imran Tahir":8.87,"A Mishra":7.77,"JP Duminy":7.53,"A Nehra":7.31,"MM Sharma":8.46,"IC Pandey":7.35,"R Ashwin":5.87,"DJ Bravo":8.45,"Sandeep Sharma":7.18,"Anureet Singh":9.23,"AR Patel":8.55,"Karanveer Singh":11.36,"MG Johnson":9.52,"TG Southee":9.11,"CH Morris":7.81,"DS Kulkarni":8.29,"JP Faulkner":9.62,"PV Tambe":7.85,"STR Binny":7.53,"B Kumar":8.11,"TA Boult":8.54,"I Sharma":11.5,"KV Sharma":8.49,"RS Bopara":8.2,"Parvez Rasool":6.2,"RA Jadeja":7.83,"SA Abbott":11.4,"HV Patel":7.73,"VR Aaron":10.38,"AN Ahmed":10.75,"DJG Sammy":8.67,"YS Chahal":8.88,"KC Cariappa":14,"YK Pathan":10,"DJ Hooda":8.64,"JD Unadkat":10,"AD Mathews":8.3,"Yuvraj Singh":8.33,"P Suyal":9.7,"J Suchith":8.67,"KA Pollard":9.55,"R Dhawan":9.25,"P Kumar":9.39,"A Ashish Reddy":8.5,"S Gopal":10.62,"PJ Cummins":10.3,"GB Hogg":7.05,"P Negi":8.63,"RG More":10.8,"GJ Maxwell":9.7,"DW Steyn":9,"NLTC Perera":9.17,"Ankit Sharma":8.14,"SR Watson":9.41,"Iqbal Abdulla":7.89,"D Wiese":8.5,"MJ McClenaghan":8.4,"HH Pandya":10.47,"Shivam Sharma":14.67,"R Tewatia":10.33,"J Botha":8.2,"MC Henriques":6.56,"Bipul Sharma":7.14,"MA Starc":7.12,"S Nadeem":6.14,"V Kohli":5.45,"M Vijay":7,"Z Khan":6.58,"SK Raina":7.83,"SN Thakur":13,"J Theron":10.25,"GS Sandhu":10.75,"R Bhatia":9.4,"RN ten Doeschate":4,"S Aravind":7.33,"M de Lange":7.5,"BE Hendricks":8.62,"Gurkeerat Singh":7.33,"J Yadav":4.14,"AB Dinda":12.6,"Azhar Mahmood":13.67,"BB Sran":12,"CH Gayle":8,"DR Smith":8.5},"2016":{"RP Singh":9.5,"I Sharma":10.07,"MR Marsh":5,"R Bhatia":7.32,"M Ashwin":8.6,"R Ashwin":7.3,"MJ McClenaghan":8.42,"JJ Bumrah":7.94,"R Vinay Kumar":7.22,"S Gopal":6.33,"Harbhajan Singh":8.2,"HH Pandya":9.3,"AD Russell":8.25,"UT Yadav":9.46,"JW Hastings":5.55,"C Munro":7.5,"GB Hogg":9,"PP Chawla":7.73,"NM Coulter-Nile":8,"Z Khan":7.81,"CH Morris":7.27,"CR Brathwaite":8.29,"A Mishra":7.61,"P Kumar":7.92,"PJ Sangwan":12.25,"JP Faulkner":9.88,"S Ladda":10.5,"RA Jadeja":7.97,"DJ Bravo":8.96,"Sandeep Sharma":7.48,"MG Johnson":9.82,"MM Sharma":8.45,"MP Stoinis":8.83,"AR Patel":8.26,"P Sahu":8.69,"A Nehra":7.69,"B Kumar":7.62,"Mustafizur Rahman":7,"MC Henriques":8.04,"KV Sharma":10.65,"A Ashish Reddy":10.43,"AF Milne":11,"SR Watson":8.67,"Parvez Rasool":9.29,"HV Patel":10.5,"YS Chahal":8.32,"TG Southee":7.74,"J Suchith":15.5,"Kuldeep Yadav":8.5,"SB Jakati":9.05,"PV Tambe":8.94,"P Negi":9.33,"J Yadav":7.35,"GJ Maxwell":9,"M Morkel":8.42,"Shakib Al Hasan":7.97,"SP Narine":7.27,"BB Sran":8.48,"DS Kulkarni":7.45,"KH Pandya":7.64,"KJ Abbott":11.38,"Ankit Sharma":7.64,"IK Pathan":7.63,"NLTC Perera":9.83,"Mohammed Shami":10.01,"S Aravind":7.61,"D Wiese":12.25,"Bipul Sharma":8.79,"YK Pathan":5.5,"VR Aaron":9.68,"KW Richardson":9.86,"Iqbal Abdulla":8.64,"STR Binny":7.88,"DJ Hooda":7.46,"DW Steyn":8.5,"SK Raina":8.4,"T Shamsi":9.44,"KA Pollard":13.67,"Imran Tahir":8.81,"R Dhawan":8,"R Sathish":9.83,"JA Morkel":13.2,"AB Dinda":7.74,"S Nadeem":8.47,"JP Duminy":7.86,"DR Smith":8.56,"JD Unadkat":16.33,"S Kaushik":8.48,"JO Holder":8.08,"KC Cariappa":9.41,"Gurkeerat Singh":7.75,"SM Boland":8,"Swapnil Singh":9.67,"Yuvraj Singh":8.43,"CJ Jordan":9.5,"A Zampa":6.88,"Anureet Singh":7.33,"V Kohli":13,"CH Gayle":6.5,"Sachin Baby":4.8,"AS Rajpoot":9.18,"BCJ Cutting":7.16,"M Vijay":8,"N Rana":3,"DL Chahar":8.4,"KS Williamson":7,"TA Boult":9.75},"2017":{"TS Mills":8.8,"A Choudhary":8.55,"YS Chahal":8.07,"S Aravind":9.11,"SR Watson":9.17,"TM Head":10.13,"STR Binny":8.33,"A Nehra":9.35,"B Kumar":7.34,"BCJ Cutting":9.71,"Rashid Khan":6.81,"DJ Hooda":10.5,"MC Henriques":10.33,"Bipul Sharma":8.02,"AB Dinda":12.1,"DL Chahar":10.71,"BA Stokes":7.43,"Imran Tahir":7.87,"A Zampa":8.27,"R Bhatia":7.86,"TG Southee":9.7,"HH Pandya":8.42,"MJ McClenaghan":9.48,"JJ Bumrah":7.54,"KH Pandya":7,"KA Pollard":16.36,"TA Boult":9.31,"PP Chawla":8.95,"SP Narine":6.98,"CR Woakes":8.93,"Kuldeep Yadav":8.41,"YK Pathan":10.25,"P Kumar":9.33,"DS Kulkarni":9.19,"MS Gony":16,"S Kaushik":9.91,"DR Smith":11.62,"SB Jakati":10.4,"Sandeep Sharma":8.38,"MM Sharma":9.02,"AR Patel":7.63,"T Natarajan":9.16,"MP Stoinis":10.57,"Swapnil Singh":8.71,"DT Christian":7.57,"RD Chahar":8.43,"Z Khan":8.04,"CH Morris":7.77,"PJ Cummins":8.51,"S Nadeem":6.67,"A Mishra":8.88,"CR Brathwaite":11.17,"B Stanlake":8.75,"Iqbal Abdulla":11,"P Negi":6.28,"SK Raina":8.5,"Tejas Baroka":9.43,"Basil Thampi":9.58,"SL Malinga":8.65,"Harbhajan Singh":6.56,"AS Rajpoot":8.07,"VR Aaron":8.5,"CJ Anderson":9.93,"Mustafizur Rahman":12.75,"UT Yadav":8.91,"C de Grandhomme":8.5,"I Sharma":10.56,"GJ Maxwell":6.63,"S Badree":7.64,"AJ Tye":6.95,"RA Jadeja":9.26,"Ankit Sharma":16,"LH Ferguson":7.38,"SN Thakur":8.36,"KC Cariappa":8.47,"MM Patel":8.29,"AF Milne":10.07,"JD Unadkat":7.2,"NM Coulter-Nile":8.19,"Mohammed Shami":9.54,"AD Mathews":11.4,"BB Sran":14.5,"S Kaul":8.5,"Mohammad Nabi":5.36,"J Yadav":7.17,"Mohammed Siraj":9.3,"Yuvraj Singh":11.5,"JP Faulkner":10.27,"Shakib Al Hasan":11.33,"K Rabada":9.28,"MG Johnson":7.35,"Washington Sundar":6.3,"SS Agarwal":10.5,"NB Singh":4.5,"KV Sharma":7.08,"RA Tripathi":12,"Ankit Soni":7.98,"Anureet Singh":13,"IK Pathan":13,"PJ Sangwan":10.17,"MN Samuels":11.33,"MJ Henry":14.2,"R Tewatia":5.67,"R Vinay Kumar":10.33,"Avesh Khan":6,"HV Patel":10.75,"CJ Jordan":10},"2018":{"DL Chahar":7.94,"SR Watson":9.32,"Harbhajan Singh":8.54,"RA Jadeja":7.93,"M Wood":13,"Imran Tahir":9.68,"DJ Bravo":10.47,"MJ McClenaghan":9.07,"Mustafizur Rahman":8.58,"JJ Bumrah":7.54,"HH Pandya":9.73,"M Markande":8.82,"R Ashwin":8.35,"MM Sharma":11.53,"M Ur Rahman":7.31,"AR Patel":8.69,"AJ Tye":8.7,"MP Stoinis":11.09,"TA Boult":9.46,"Mohammed Shami":10.55,"A Mishra":7.32,"CH Morris":11.14,"DT Christian":9.38,"R Tewatia":8.05,"R Vinay Kumar":17.48,"PP Chawla":8.68,"Kuldeep Yadav":8.49,"SP Narine":7.93,"MG Johnson":10.81,"AD Russell":9.96,"N Rana":7.3,"YS Chahal":8.01,"CR Woakes":11.45,"Washington Sundar":10.1,"UT Yadav":8.36,"K Khejroliya":10.89,"B Kumar":7.99,"B Stanlake":8.38,"Shakib Al Hasan":8.16,"S Kaul":8.71,"Rashid Khan":7.01,"DS Kulkarni":9.93,"JD Unadkat":9.81,"K Gowtham":8.29,"B Laughlin":10.52,"S Gopal":7.87,"BA Stokes":8.68,"D Short":9,"SN Thakur":9.64,"T Curran":11.9,"S Nadeem":11,"Sandeep Sharma":7.82,"PJ Sangwan":10.5,"BCJ Cutting":10.18,"KH Pandya":7.34,"GJ Maxwell":8.38,"A Dananjaya":12,"S Mavi":10.29,"P Negi":12.25,"BB Sran":11.32,"Yuvraj Singh":12,"V Shankar":12.4,"Mohammed Siraj":9.73,"CJ Anderson":14.31,"CJ Jordan":10,"DJ Hooda":9,"STR Binny":17.5,"KV Sharma":9.68,"AS Rajpoot":9.4,"HV Patel":10.17,"J Archer":8.99,"Avesh Khan":11,"L Plunkett":9.4,"Mohammad Nabi":9.4,"Basil Thampi":11.51,"MK Tiwary":13,"I Sodhi":6,"M Lomror":9,"YK Pathan":7,"TG Southee":9.45,"M Ashwin":8.29,"L Ngidi":6.73,"KM Asif":12.83,"JP Duminy":12,"C de Grandhomme":9.73,"D Willey":9.8,"P Krishna":9.68,"Anureet Singh":10.5,"M Ali":7.67,"Ankit Sharma":11,"J Searles":13.14,"S Lamichhane":7.58,"J Dala":11.67,"CR Brathwaite":9.93,"K Ahmed":13.67},"2019":{"DL Chahar":7.74,"Harbhajan Singh":7.39,"SK Raina":6,"Imran Tahir":7.04,"RA Jadeja":6.53,"DJ Bravo":8.7,"YS Chahal":8.39,"N Saini":9.01,"M Ali":6.79,"UT Yadav":10.29,"Mohammed Siraj":10.19,"S Dube":5.4,"P Krishna":10.02,"PP Chawla":9.24,"L Ferguson":11.29,"SP Narine":8.35,"Kuldeep Yadav":8.79,"AD Russell":9.61,"N Rana":9.5,"B Kumar":8.22,"Shakib Al Hasan":8.82,"S Sharma":8.6,"S Kaul":9.3,"Rashid Khan":6.81,"R Salam":11.25,"MJ McClenaghan":8.33,"JJ Bumrah":7.38,"HH Pandya":9.84,"KH Pandya":7.5,"BCJ Cutting":13.5,"TA Boult":8.95,"I Sharma":8.47,"K Rabada":8.38,"R Tewatia":6.79,"K Paul":9.55,"AR Patel":7.31,"DS Kulkarni":9.89,"K Gowtham":8.88,"J Archer":7.55,"BA Stokes":13.01,"JD Unadkat":11.3,"S Gopal":7.38,"S Curran":10.18,"M Ur Rahman":11.11,"Mohammed Shami":9.13,"R Ashwin":7.54,"AS Rajpoot":10.5,"SN Thakur":9.91,"A Mishra":6.82,"V Chakravarthy":11.67,"H Viljoen":10.78,"AJ Tye":10.82,"Mandeep Singh":13,"C de Grandhomme":11.2,"SL Malinga":10.64,"M Markande":10,"S Nadeem":10.22,"V Shankar":8.94,"M Ashwin":7.85,"S Lamichhane":9.22,"CH Morris":10,"HV Patel":10.63,"P R Barman":14,"Mohammad Nabi":7.13,"M Santner":7.5,"Avesh Khan":10.33,"H Vihari":9,"VR Aaron":11.83,"STR Binny":6.42,"MP Stoinis":9.12,"MM Sharma":9,"J Behrendorff":9.16,"RD Chahar":6.74,"TG Southee":15.11,"P Negi":9.53,"S Kuggeleijn":9.13,"YK Pathan":8,"A Joseph":10.85,"H Gurney":9.15,"S Midhun":16,"R Parag":8.64,"CR Brathwaite":10.67,"L Livingstone":13,"SN Khan":18,"K Ahmed":8.9,"DJ Hooda":9.69,"Ankit Sharma":11,"I Sodhi":9.49,"A Singh":13,"KV Sharma":11.65,"J Yadav":7.29,"DW Steyn":9.88,"S Rutherford":9.66,"H Brar":9.6,"P Raj":12,"KC Cariappa":17.5,"Washington Sundar":8.44,"O Thomas":9.4,"A Roy":7,"BB Sran":13,"S Warrier":7.33,"K Khejroliya":9.6,"J Suchith":7,"Basil Thampi":10.08}}}